[
    {
        "id": "message-1",
        "block": "block-1",
        "next": {
            "type": "message",
            "id": "message-2"
        },
        "isEnd": false,
        "type": "message",
        "text": "hello"
    },
    {
        "id": "message-2",
        "block": "block-1",
        "next": {
            "type": "block",
            "id": "block-2",
            "after": "message-3"
        },
        "isEnd": false,
        "type": "message",
        "text": "testing"
    },
    {
        "id": "message-3",
        "block": "block-1",
        "next": {
            "type": "message",
            "id": "message-9"
        },
        "isEnd": false,
        "type": "message",
        "text": "returned to block 1"
    },
    {
        "id": "message-9",
        "block": "block-1",
        "next": {},
        "isEnd": false,
        "type": "question",
        "quick_replies": [
            {
                "content_type": "text",
                "title": "Yes",
                "payload": "message-11"
            },
            {
                "content_type": "text",
                "title": "No",
                "payload": "message-12"
            }  
        ],
        "text": "Quick Reply Questions:"
    },
    {
        "id": "message-11",
        "block": "block-1",
        "next": {
            "type": "message",
            "id": "message-13"
        },
        "isEnd": false,
        "type": "message",
        "text": "Bot saw Yes"
    },
    {
        "id": "message-12",
        "block": "block-1",
        "next": {
            "type": "message",
            "id": "message-13"
        },
        "isEnd": false,
        "type": "message",
        "text": "Bot saw No"
    },
    {
        "id": "message-13",
        "block": "block-1",
        "next": {},
        "isEnd": true,
        "type": "message",
        "text": "Block 1 End"
    },
    {
        "id": "message-14",
        "block": "block-2",
        "next": {
            "type": "message",
            "id": "message-15"
        },
        "isEnd": false,
        "type": "question",
        "text": "How are you?"
    },
    {
        "id": "message-15",
        "block": "block-2",
        "next": {
            "type": "message",
            "id": "message-16"
        },
        "isEnd": false,
        "type": "message",
        "text": "Bot Reply to text input"
    },
    {
        "id": "message-16",
        "block": "block-2",
        "next": {
            "type": "block",
            "id": "block-3",
            "after": "message-17"
        },
        "isEnd": false,
        "type": "message",
        "text": "Insert Block 3 Next"
    },
    {
        "id": "message-17",
        "block": "block-2",
        "next": {},
        "isEnd": true,
        "type": "message",
        "text": "Returned to Block 2"
    },
    {
        "id": "message-18",
        "block": "block-3",
        "next": {
            "type": "question",
            "id": "message-19"
        },
        "isEnd": false,
        "type": "message",
        "text": "Block 3"
    },
    {
        "id": "message-19",
        "block": "block-3",
        "next": {
            "type": "image",
            "id": "message-20"
        },
        "isEnd": false,
        "type": "question",
        "text": "Question in Block 3"
    },
    {
        "id": "message-20",
        "block": "block-3",
        "next": {
            "type": "video",
            "id": "message-21"
        },
        "isEnd": false,
        "type": "image",
        "text": ""
    },
    {
        "id": "message-21",
        "block": "block-3",
        "next": {
            "type": "message",
            "id": "message-22"
        },
        "isEnd": false,
        "type": "video",
        "text": ""
    },
    {
        "id": "message-22",
        "block": "block-3",
        "next": {},
        "isEnd": true,
        "type": "message",
        "text": "Leaving Block 3"
    }
]